pynstal-0.1.4.dist-info/licenses/LICENSE
pythonprojectmanager/__init__.py
pythonprojectmanager/create_venv.py
pythonprojectmanager/handle_data.py
pythonprojectmanager/main.py
pythonprojectmanager/templates.json
pynstal-0.1.4.dist-info/METADATA
pynstal-0.1.4.dist-info/WHEEL
pynstal-0.1.4.dist-info/entry_points.txt
pynstal-0.1.4.dist-info/top_level.txt
pynstal-0.1.4.dist-info/RECORD
