Metadata-Version: 2.4
Name: pynstal
Version: 0.1.4
Summary: CLI utility to manage Python virtual environments with auto-detection
Home-page: https://github.com/sho96/PythonProjectManager
Author: sho96
Author-email: shotaro962008@gmail.com
Keywords: python virtualenv venv management cli
Classifier: Development Status :: 3 - Alpha
Classifier: Intended Audience :: Developers
Classifier: License :: OSI Approved :: MIT License
Classifier: Programming Language :: Python :: 3
Classifier: Programming Language :: Python :: 3.10
Classifier: Programming Language :: Python :: 3.11
Classifier: Programming Language :: Python :: 3.12
Classifier: Programming Language :: Python :: 3.13
Classifier: Operating System :: OS Independent
Classifier: Topic :: System :: Systems Administration
Classifier: Topic :: Utilities
Requires-Python: >=3.10
License-File: LICENSE
Dynamic: license-file
